ipython_gpt/__init__.py
ipython_gpt/api_client.py
ipython_gpt/displays.py
ipython_gpt/subcommands.py
ipython_gpt-0.0.6.dist-info/LICENSE
ipython_gpt-0.0.6.dist-info/METADATA
ipython_gpt-0.0.6.dist-info/WHEEL
ipython_gpt-0.0.6.dist-info/RECORD
