Metadata-Version: 2.1
Name: ipython-gpt
Version: 0.0.6
Summary: A Jupyter/IPython extension to use ChatGPT
Home-page: https://github.com/santiagobasulto/ipython-gpt
License: MIT
Keywords: ipython,jupyter,chatgpt,openai
Author: Santiago Basulto
Author-email: santiago.basulto@gmail.com
Requires-Python: >=3.8,<4.0
Classifier: Development Status :: 3 - Alpha
Classifier: Framework :: IPython
Classifier: Intended Audience :: Developers
Classifier: License :: OSI Approved :: MIT License
Classifier: Programming Language :: Python
Classifier: Programming Language :: Python :: 3
Classifier: Programming Language :: Python :: 3.8
Classifier: Programming Language :: Python :: 3.9
Classifier: Programming Language :: Python :: 3.10
Classifier: Programming Language :: Python :: 3.11
Classifier: Topic :: Utilities
Requires-Dist: ipython (>=8.12.0,<9.0.0)
Project-URL: Repository, https://github.com/santiagobasulto/ipython-gpt
